rikai/__init__.py
rikai/__version__.py
rikai/conf.py
rikai/exceptions.py
rikai/io.py
rikai/logging.py
rikai/mixin.py
rikai/numpy.py
rikai/viz.py
rikai/contrib/__init__.py
rikai/contrib/s3.py
rikai/contrib/datasets/__init__.py
rikai/contrib/datasets/coco.py
rikai/contrib/tfhub/__init__.py
rikai/contrib/tfhub/tensorflow/__init__.py
rikai/contrib/tfhub/tensorflow/ssd.py
rikai/contrib/torch/__init__.py
rikai/contrib/torch/detections.py
rikai/contrib/torch/transforms/__init__.py
rikai/contrib/torch/transforms/fasterrcnn_resnet50_fpn.py
rikai/contrib/torch/transforms/ssd.py
rikai/contrib/torchhub/__init__.py
rikai/contrib/torchhub/pytorch/__init__.py
rikai/contrib/torchhub/pytorch/vision/__init__.py
rikai/contrib/torchhub/pytorch/vision/resnet.py
rikai/contrib/video/__init__.py
rikai/contrib/video/functions.py
rikai/internal/__init__.py
rikai/internal/reflection.py
rikai/internal/uri_utils.py
rikai/parquet/__init__.py
rikai/parquet/dataset.py
rikai/parquet/resolver.py
rikai/parquet/writer.py
rikai/pytorch/__init__.py
rikai/pytorch/data.py
rikai/pytorch/pandas.py
rikai/pytorch/transforms.py
rikai/pytorch/vision.py
rikai/pytorch/models/__init__.py
rikai/pytorch/models/convnext.py
rikai/pytorch/models/efficientnet.py
rikai/pytorch/models/fasterrcnn.py
rikai/pytorch/models/feature_extractor.py
rikai/pytorch/models/keypointrcnn.py
rikai/pytorch/models/maskrcnn.py
rikai/pytorch/models/resnet.py
rikai/pytorch/models/retinanet.py
rikai/pytorch/models/ssd.py
rikai/pytorch/models/ssd_class_scores.py
rikai/pytorch/models/torch.py
rikai/sklearn/__init__.py
rikai/sklearn/models.py
rikai/spark/__init__.py
rikai/spark/utils.py
rikai/spark/functions/__init__.py
rikai/spark/functions/geometry.py
rikai/spark/functions/io.py
rikai/spark/functions/vision.py
rikai/spark/sql/__init__.py
rikai/spark/sql/exceptions.py
rikai/spark/sql/model.py
rikai/spark/sql/schema.py
rikai/spark/sql/codegen/__init__.py
rikai/spark/sql/codegen/base.py
rikai/spark/sql/codegen/dummy.py
rikai-0.1.15.dist-info/METADATA
rikai-0.1.15.dist-info/WHEEL
rikai-0.1.15.dist-info/top_level.txt
rikai-0.1.15.dist-info/RECORD
