Metadata-Version: 2.1
Name: rikai
Version: 0.1.15
Summary: UNKNOWN
Home-page: https://github.com/eto-ai/rikai
Author: Rikai authors
Author-email: rikai-dev@eto.ai
License: Apache License, Version 2.0
Platform: UNKNOWN
Classifier: License :: OSI Approved :: Apache Software License
Classifier: Operating System :: OS Independent
Classifier: Programming Language :: Python :: 3
Classifier: Topic :: Software Development :: Libraries
Requires-Python: >=3.7
Requires-Dist: antlr4-python3-runtime (==4.11.1)
Requires-Dist: ipython (!=8.0.0,>=7.31.1)
Requires-Dist: jsonschema
Requires-Dist: numpy
Requires-Dist: opencv-python-headless
Requires-Dist: pandas
Requires-Dist: Pillow
Requires-Dist: pyarrow (>=6.0)
Requires-Dist: pyspark (==3.2.*)
Requires-Dist: pyyaml
Requires-Dist: requests
Requires-Dist: semver
Provides-Extra: all
Requires-Dist: scikit-learn ; extra == 'all'
Requires-Dist: torch (>=1.8.1) ; extra == 'all'
Requires-Dist: torchvision (>=0.10.0) ; extra == 'all'
Requires-Dist: tensorflow (>=2.5.0) ; extra == 'all'
Requires-Dist: tensorflow-hub ; extra == 'all'
Requires-Dist: matplotlib ; extra == 'all'
Requires-Dist: jupyterlab ; extra == 'all'
Requires-Dist: gcsfs ; extra == 'all'
Requires-Dist: sphinx ; extra == 'all'
Requires-Dist: sphinx-material ; extra == 'all'
Requires-Dist: ffmpeg-python ; extra == 'all'
Requires-Dist: scenedetect (<0.6) ; extra == 'all'
Requires-Dist: pafy ; extra == 'all'
Requires-Dist: youtube-dl ; extra == 'all'
Requires-Dist: mlflow (==1.26.1) ; extra == 'all'
Requires-Dist: boto3 ; extra == 'all'
Requires-Dist: botocore ; extra == 'all'
Provides-Extra: aws
Requires-Dist: boto3 ; extra == 'aws'
Requires-Dist: botocore ; extra == 'aws'
Provides-Extra: dev
Requires-Dist: black (==22.1.0) ; extra == 'dev'
Requires-Dist: click (<8.1) ; extra == 'dev'
Requires-Dist: bump2version ; extra == 'dev'
Requires-Dist: flake8 ; extra == 'dev'
Requires-Dist: isort ; extra == 'dev'
Requires-Dist: pylint ; extra == 'dev'
Requires-Dist: pytest-timeout ; extra == 'dev'
Requires-Dist: pytest ; extra == 'dev'
Requires-Dist: requests-mock ; extra == 'dev'
Requires-Dist: wheel ; extra == 'dev'
Provides-Extra: docs
Requires-Dist: sphinx ; extra == 'docs'
Requires-Dist: sphinx-material ; extra == 'docs'
Provides-Extra: gcp
Requires-Dist: gcsfs ; extra == 'gcp'
Provides-Extra: jupyter
Requires-Dist: matplotlib ; extra == 'jupyter'
Requires-Dist: jupyterlab ; extra == 'jupyter'
Provides-Extra: mlflow
Requires-Dist: mlflow (==1.26.1) ; extra == 'mlflow'
Provides-Extra: pytorch
Requires-Dist: torch (>=1.8.1) ; extra == 'pytorch'
Requires-Dist: torchvision (>=0.10.0) ; extra == 'pytorch'
Provides-Extra: sklearn
Requires-Dist: scikit-learn ; extra == 'sklearn'
Provides-Extra: tf
Requires-Dist: tensorflow (>=2.5.0) ; extra == 'tf'
Requires-Dist: tensorflow-hub ; extra == 'tf'
Provides-Extra: video
Requires-Dist: ffmpeg-python ; extra == 'video'
Requires-Dist: scenedetect (<0.6) ; extra == 'video'
Provides-Extra: youtube
Requires-Dist: pafy ; extra == 'youtube'
Requires-Dist: youtube-dl ; extra == 'youtube'
